[{"specific":["https://w3id.org/reliedu/didactics/"],"specifi":["https://w3id.org/reliedu/didactics/"],"specif":["https://w3id.org/reliedu/didactics/"],"speci":["https://w3id.org/reliedu/didactics/"],"spec":["https://w3id.org/reliedu/didactics/"],"spe":["https://w3id.org/reliedu/didactics/"],"sp":["https://w3id.org/reliedu/didactics/"],"s":["https://w3id.org/reliedu/didactics/"],"pecific":["https://w3id.org/reliedu/didactics/"],"pecifi":["https://w3id.org/reliedu/didactics/"],"pecif":["https://w3id.org/reliedu/didactics/"],"peci":["https://w3id.org/reliedu/didactics/"],"pec":["https://w3id.org/reliedu/didactics/"],"pe":["https://w3id.org/reliedu/didactics/"],"p":["https://w3id.org/reliedu/didactics/"],"ecific":["https://w3id.org/reliedu/didactics/"],"ecifi":["https://w3id.org/reliedu/didactics/"],"ecif":["https://w3id.org/reliedu/didactics/"],"eci":["https://w3id.org/reliedu/didactics/"],"ec":["https://w3id.org/reliedu/didactics/"],"e":["https://w3id.org/reliedu/didactics/"],"cific":["https://w3id.org/reliedu/didactics/"],"cifi":["https://w3id.org/reliedu/didactics/"],"cif":["https://w3id.org/reliedu/didactics/"],"ci":["https://w3id.org/reliedu/didactics/"],"c":["https://w3id.org/reliedu/didactics/"],"ific":["https://w3id.org/reliedu/didactics/"],"ifi":["https://w3id.org/reliedu/didactics/"],"if":["https://w3id.org/reliedu/didactics/"],"i":["https://w3id.org/reliedu/didactics/"],"fic":["https://w3id.org/reliedu/didactics/"],"fi":["https://w3id.org/reliedu/didactics/"],"f":["https://w3id.org/reliedu/didactics/"],"ic":["https://w3id.org/reliedu/didactics/"]},{"didactic":["https://w3id.org/reliedu/didactics/"],"didacti":["https://w3id.org/reliedu/didactics/"],"didact":["https://w3id.org/reliedu/didactics/"],"didac":["https://w3id.org/reliedu/didactics/"],"dida":["https://w3id.org/reliedu/didactics/"],"did":["https://w3id.org/reliedu/didactics/"],"di":["https://w3id.org/reliedu/didactics/"],"d":["https://w3id.org/reliedu/didactics/"],"idactic":["https://w3id.org/reliedu/didactics/"],"idacti":["https://w3id.org/reliedu/didactics/"],"idact":["https://w3id.org/reliedu/didactics/"],"idac":["https://w3id.org/reliedu/didactics/"],"ida":["https://w3id.org/reliedu/didactics/"],"id":["https://w3id.org/reliedu/didactics/"],"dactic":["https://w3id.org/reliedu/didactics/"],"dacti":["https://w3id.org/reliedu/didactics/"],"dact":["https://w3id.org/reliedu/didactics/"],"dac":["https://w3id.org/reliedu/didactics/"],"da":["https://w3id.org/reliedu/didactics/"],"actic":["https://w3id.org/reliedu/didactics/"],"acti":["https://w3id.org/reliedu/didactics/"],"act":["https://w3id.org/reliedu/didactics/"],"ac":["https://w3id.org/reliedu/didactics/"],"a":["https://w3id.org/reliedu/didactics/"],"principles":["https://w3id.org/reliedu/didactics/"],"principle":["https://w3id.org/reliedu/didactics/"],"principl":["https://w3id.org/reliedu/didactics/"],"princip":["https://w3id.org/reliedu/didactics/"],"princi":["https://w3id.org/reliedu/didactics/"],"princ":["https://w3id.org/reliedu/didactics/"],"prin":["https://w3id.org/reliedu/didactics/"],"pri":["https://w3id.org/reliedu/didactics/"],"pr":["https://w3id.org/reliedu/didactics/"],"rinciples":["https://w3id.org/reliedu/didactics/"],"rinciple":["https://w3id.org/reliedu/didactics/"],"rincipl":["https://w3id.org/reliedu/didactics/"],"rincip":["https://w3id.org/reliedu/didactics/"],"rinci":["https://w3id.org/reliedu/didactics/"],"rinc":["https://w3id.org/reliedu/didactics/"],"rin":["https://w3id.org/reliedu/didactics/"],"ri":["https://w3id.org/reliedu/didactics/"],"r":["https://w3id.org/reliedu/didactics/"],"inciples":["https://w3id.org/reliedu/didactics/"],"inciple":["https://w3id.org/reliedu/didactics/"],"incipl":["https://w3id.org/reliedu/didactics/"],"incip":["https://w3id.org/reliedu/didactics/"],"inci":["https://w3id.org/reliedu/didactics/"],"inc":["https://w3id.org/reliedu/didactics/"],"in":["https://w3id.org/reliedu/didactics/"],"and":["https://w3id.org/reliedu/didactics/"],"an":["https://w3id.org/reliedu/didactics/"],"approaches":["https://w3id.org/reliedu/didactics/"],"approache":["https://w3id.org/reliedu/didactics/"],"approach":["https://w3id.org/reliedu/didactics/"],"approac":["https://w3id.org/reliedu/didactics/"],"approa":["https://w3id.org/reliedu/didactics/"],"appro":["https://w3id.org/reliedu/didactics/"],"appr":["https://w3id.org/reliedu/didactics/"],"app":["https://w3id.org/reliedu/didactics/"],"ap":["https://w3id.org/reliedu/didactics/"]},{"ctic":["https://w3id.org/reliedu/didactics/"],"cti":["https://w3id.org/reliedu/didactics/"],"ct":["https://w3id.org/reliedu/didactics/"],"tic":["https://w3id.org/reliedu/didactics/"],"ti":["https://w3id.org/reliedu/didactics/"],"t":["https://w3id.org/reliedu/didactics/"],"nciples":["https://w3id.org/reliedu/didactics/"],"nciple":["https://w3id.org/reliedu/didactics/"],"ncipl":["https://w3id.org/reliedu/didactics/"],"ncip":["https://w3id.org/reliedu/didactics/"],"nci":["https://w3id.org/reliedu/didactics/"],"nc":["https://w3id.org/reliedu/didactics/"],"n":["https://w3id.org/reliedu/didactics/"],"ciples":["https://w3id.org/reliedu/didactics/"],"ciple":["https://w3id.org/reliedu/didactics/"],"cipl":["https://w3id.org/reliedu/didactics/"],"cip":["https://w3id.org/reliedu/didactics/"],"iples":["https://w3id.org/reliedu/didactics/"],"iple":["https://w3id.org/reliedu/didactics/"],"ipl":["https://w3id.org/reliedu/didactics/"],"ip":["https://w3id.org/reliedu/didactics/"],"ples":["https://w3id.org/reliedu/didactics/"],"ple":["https://w3id.org/reliedu/didactics/"],"pl":["https://w3id.org/reliedu/didactics/"],"nd":["https://w3id.org/reliedu/didactics/"],"pproaches":["https://w3id.org/reliedu/didactics/"],"pproache":["https://w3id.org/reliedu/didactics/"],"pproach":["https://w3id.org/reliedu/didactics/"],"pproac":["https://w3id.org/reliedu/didactics/"],"pproa":["https://w3id.org/reliedu/didactics/"],"ppro":["https://w3id.org/reliedu/didactics/"],"ppr":["https://w3id.org/reliedu/didactics/"],"pp":["https://w3id.org/reliedu/didactics/"],"proaches":["https://w3id.org/reliedu/didactics/"],"proache":["https://w3id.org/reliedu/didactics/"],"proach":["https://w3id.org/reliedu/didactics/"],"proac":["https://w3id.org/reliedu/didactics/"],"proa":["https://w3id.org/reliedu/didactics/"],"pro":["https://w3id.org/reliedu/didactics/"],"roaches":["https://w3id.org/reliedu/didactics/"],"roache":["https://w3id.org/reliedu/didactics/"],"roach":["https://w3id.org/reliedu/didactics/"],"roac":["https://w3id.org/reliedu/didactics/"],"roa":["https://w3id.org/reliedu/didactics/"],"ro":["https://w3id.org/reliedu/didactics/"],"oaches":["https://w3id.org/reliedu/didactics/"],"oache":["https://w3id.org/reliedu/didactics/"],"oach":["https://w3id.org/reliedu/didactics/"],"oac":["https://w3id.org/reliedu/didactics/"],"oa":["https://w3id.org/reliedu/didactics/"],"o":["https://w3id.org/reliedu/didactics/"],"religious":["https://w3id.org/reliedu/didactics/"],"religiou":["https://w3id.org/reliedu/didactics/"],"religio":["https://w3id.org/reliedu/didactics/"],"religi":["https://w3id.org/reliedu/didactics/"],"relig":["https://w3id.org/reliedu/didactics/"],"reli":["https://w3id.org/reliedu/didactics/"],"rel":["https://w3id.org/reliedu/didactics/"],"re":["https://w3id.org/reliedu/didactics/"],"eligious":["https://w3id.org/reliedu/didactics/"],"eligiou":["https://w3id.org/reliedu/didactics/"],"eligio":["https://w3id.org/reliedu/didactics/"],"eligi":["https://w3id.org/reliedu/didactics/"],"elig":["https://w3id.org/reliedu/didactics/"],"eli":["https://w3id.org/reliedu/didactics/"],"el":["https://w3id.org/reliedu/didactics/"],"ligious":["https://w3id.org/reliedu/didactics/"],"ligiou":["https://w3id.org/reliedu/didactics/"],"ligio":["https://w3id.org/reliedu/didactics/"],"ligi":["https://w3id.org/reliedu/didactics/"],"lig":["https://w3id.org/reliedu/didactics/"],"li":["https://w3id.org/reliedu/didactics/"],"education":["https://w3id.org/reliedu/didactics/"],"educatio":["https://w3id.org/reliedu/didactics/"],"educati":["https://w3id.org/reliedu/didactics/"],"educat":["https://w3id.org/reliedu/didactics/"],"educa":["https://w3id.org/reliedu/didactics/"],"educ":["https://w3id.org/reliedu/didactics/"],"edu":["https://w3id.org/reliedu/didactics/"],"ed":["https://w3id.org/reliedu/didactics/"],"ducation":["https://w3id.org/reliedu/didactics/"],"ducatio":["https://w3id.org/reliedu/didactics/"],"ducati":["https://w3id.org/reliedu/didactics/"],"ducat":["https://w3id.org/reliedu/didactics/"],"duca":["https://w3id.org/reliedu/didactics/"],"duc":["https://w3id.org/reliedu/didactics/"],"du":["https://w3id.org/reliedu/didactics/"],"characterize":["https://w3id.org/reliedu/didactics/"],"characteriz":["https://w3id.org/reliedu/didactics/"],"characteri":["https://w3id.org/reliedu/didactics/"],"character":["https://w3id.org/reliedu/didactics/"],"characte":["https://w3id.org/reliedu/didactics/"],"charact":["https://w3id.org/reliedu/didactics/"],"charac":["https://w3id.org/reliedu/didactics/"],"chara":["https://w3id.org/reliedu/didactics/"],"char":["https://w3id.org/reliedu/didactics/"],"cha":["https://w3id.org/reliedu/didactics/"]},{"les":["https://w3id.org/reliedu/didactics/"],"le":["https://w3id.org/reliedu/didactics/"],"l":["https://w3id.org/reliedu/didactics/"],"es":["https://w3id.org/reliedu/didactics/"],"aches":["https://w3id.org/reliedu/didactics/"],"ache":["https://w3id.org/reliedu/didactics/"],"ach":["https://w3id.org/reliedu/didactics/"],"ches":["https://w3id.org/reliedu/didactics/"],"che":["https://w3id.org/reliedu/didactics/"],"ch":["https://w3id.org/reliedu/didactics/"],"hes":["https://w3id.org/reliedu/didactics/"],"he":["https://w3id.org/reliedu/didactics/"],"h":["https://w3id.org/reliedu/didactics/"],"igious":["https://w3id.org/reliedu/didactics/"],"igiou":["https://w3id.org/reliedu/didactics/"],"igio":["https://w3id.org/reliedu/didactics/"],"igi":["https://w3id.org/reliedu/didactics/"],"ig":["https://w3id.org/reliedu/didactics/"],"gious":["https://w3id.org/reliedu/didactics/"],"giou":["https://w3id.org/reliedu/didactics/"],"gio":["https://w3id.org/reliedu/didactics/"],"gi":["https://w3id.org/reliedu/didactics/"],"g":["https://w3id.org/reliedu/didactics/"],"ious":["https://w3id.org/reliedu/didactics/"],"iou":["https://w3id.org/reliedu/didactics/"],"io":["https://w3id.org/reliedu/didactics/"],"ous":["https://w3id.org/reliedu/didactics/"],"ou":["https://w3id.org/reliedu/didactics/"],"ucation":["https://w3id.org/reliedu/didactics/"],"ucatio":["https://w3id.org/reliedu/didactics/"],"ucati":["https://w3id.org/reliedu/didactics/"],"ucat":["https://w3id.org/reliedu/didactics/"],"uca":["https://w3id.org/reliedu/didactics/"],"uc":["https://w3id.org/reliedu/didactics/"],"cation":["https://w3id.org/reliedu/didactics/"],"catio":["https://w3id.org/reliedu/didactics/"],"cati":["https://w3id.org/reliedu/didactics/"],"cat":["https://w3id.org/reliedu/didactics/"],"ca":["https://w3id.org/reliedu/didactics/"],"ation":["https://w3id.org/reliedu/didactics/"],"atio":["https://w3id.org/reliedu/didactics/"],"ati":["https://w3id.org/reliedu/didactics/"],"at":["https://w3id.org/reliedu/didactics/"],"tion":["https://w3id.org/reliedu/didactics/"],"tio":["https://w3id.org/reliedu/didactics/"],"that":["https://w3id.org/reliedu/didactics/"],"tha":["https://w3id.org/reliedu/didactics/"],"th":["https://w3id.org/reliedu/didactics/"],"hat":["https://w3id.org/reliedu/didactics/"],"ha":["https://w3id.org/reliedu/didactics/"],"haracterize":["https://w3id.org/reliedu/didactics/"],"haracteriz":["https://w3id.org/reliedu/didactics/"],"haracteri":["https://w3id.org/reliedu/didactics/"],"haracter":["https://w3id.org/reliedu/didactics/"],"haracte":["https://w3id.org/reliedu/didactics/"],"haract":["https://w3id.org/reliedu/didactics/"],"harac":["https://w3id.org/reliedu/didactics/"],"hara":["https://w3id.org/reliedu/didactics/"],"har":["https://w3id.org/reliedu/didactics/"],"aracterize":["https://w3id.org/reliedu/didactics/"],"aracteriz":["https://w3id.org/reliedu/didactics/"],"aracteri":["https://w3id.org/reliedu/didactics/"],"aracter":["https://w3id.org/reliedu/didactics/"],"aracte":["https://w3id.org/reliedu/didactics/"],"aract":["https://w3id.org/reliedu/didactics/"],"arac":["https://w3id.org/reliedu/didactics/"],"ara":["https://w3id.org/reliedu/didactics/"],"ar":["https://w3id.org/reliedu/didactics/"],"racterize":["https://w3id.org/reliedu/didactics/"],"racteriz":["https://w3id.org/reliedu/didactics/"],"racteri":["https://w3id.org/reliedu/didactics/"],"racter":["https://w3id.org/reliedu/didactics/"],"racte":["https://w3id.org/reliedu/didactics/"],"ract":["https://w3id.org/reliedu/didactics/"],"rac":["https://w3id.org/reliedu/didactics/"],"ra":["https://w3id.org/reliedu/didactics/"],"acterize":["https://w3id.org/reliedu/didactics/"],"acteriz":["https://w3id.org/reliedu/didactics/"],"acteri":["https://w3id.org/reliedu/didactics/"],"acter":["https://w3id.org/reliedu/didactics/"],"acte":["https://w3id.org/reliedu/didactics/"],"the":["https://w3id.org/reliedu/didactics/"],"material":["https://w3id.org/reliedu/didactics/"],"materia":["https://w3id.org/reliedu/didactics/"],"materi":["https://w3id.org/reliedu/didactics/"],"mater":["https://w3id.org/reliedu/didactics/"],"mate":["https://w3id.org/reliedu/didactics/"],"mat":["https://w3id.org/reliedu/didactics/"],"ma":["https://w3id.org/reliedu/didactics/"],"m":["https://w3id.org/reliedu/didactics/"],"aterial":["https://w3id.org/reliedu/didactics/"],"ateria":["https://w3id.org/reliedu/didactics/"],"ateri":["https://w3id.org/reliedu/didactics/"],"ater":["https://w3id.org/reliedu/didactics/"],"ate":["https://w3id.org/reliedu/didactics/"]},{"us":["https://w3id.org/reliedu/didactics/"],"u":["https://w3id.org/reliedu/didactics/"],"ion":["https://w3id.org/reliedu/didactics/"],"on":["https://w3id.org/reliedu/didactics/"],"cterize":["https://w3id.org/reliedu/didactics/"],"cteriz":["https://w3id.org/reliedu/didactics/"],"cteri":["https://w3id.org/reliedu/didactics/"],"cter":["https://w3id.org/reliedu/didactics/"],"cte":["https://w3id.org/reliedu/didactics/"],"terize":["https://w3id.org/reliedu/didactics/"],"teriz":["https://w3id.org/reliedu/didactics/"],"teri":["https://w3id.org/reliedu/didactics/"],"ter":["https://w3id.org/reliedu/didactics/"],"te":["https://w3id.org/reliedu/didactics/"],"erize":["https://w3id.org/reliedu/didactics/"],"eriz":["https://w3id.org/reliedu/didactics/"],"eri":["https://w3id.org/reliedu/didactics/"],"er":["https://w3id.org/reliedu/didactics/"],"rize":["https://w3id.org/reliedu/didactics/"],"riz":["https://w3id.org/reliedu/didactics/"],"ize":["https://w3id.org/reliedu/didactics/"],"iz":["https://w3id.org/reliedu/didactics/"],"terial":["https://w3id.org/reliedu/didactics/"],"teria":["https://w3id.org/reliedu/didactics/"],"erial":["https://w3id.org/reliedu/didactics/"],"eria":["https://w3id.org/reliedu/didactics/"],"rial":["https://w3id.org/reliedu/didactics/"],"ria":["https://w3id.org/reliedu/didactics/"],"ial":["https://w3id.org/reliedu/didactics/"],"ia":["https://w3id.org/reliedu/didactics/"],"these":["https://w3id.org/reliedu/didactics/"],"thes":["https://w3id.org/reliedu/didactics/"],"hese":["https://w3id.org/reliedu/didactics/"],"ese":["https://w3id.org/reliedu/didactics/"],"labels":["https://w3id.org/reliedu/didactics/"],"label":["https://w3id.org/reliedu/didactics/"],"labe":["https://w3id.org/reliedu/didactics/"],"lab":["https://w3id.org/reliedu/didactics/"],"la":["https://w3id.org/reliedu/didactics/"],"abels":["https://w3id.org/reliedu/didactics/"],"abel":["https://w3id.org/reliedu/didactics/"],"abe":["https://w3id.org/reliedu/didactics/"],"ab":["https://w3id.org/reliedu/didactics/"],"identify":["https://w3id.org/reliedu/didactics/"],"identif":["https://w3id.org/reliedu/didactics/"],"identi":["https://w3id.org/reliedu/didactics/"],"ident":["https://w3id.org/reliedu/didactics/"],"iden":["https://w3id.org/reliedu/didactics/"],"ide":["https://w3id.org/reliedu/didactics/"],"dentify":["https://w3id.org/reliedu/didactics/"],"dentif":["https://w3id.org/reliedu/didactics/"],"denti":["https://w3id.org/reliedu/didactics/"],"dent":["https://w3id.org/reliedu/didactics/"],"den":["https://w3id.org/reliedu/didactics/"],"de":["https://w3id.org/reliedu/didactics/"]},{"1":["https://w3id.org/reliedu/didactics/"],"3":["https://w3id.org/reliedu/didactics/"],"13":["https://w3id.org/reliedu/didactics/"],"ze":["https://w3id.org/reliedu/didactics/"],"z":["https://w3id.org/reliedu/didactics/"],"al":["https://w3id.org/reliedu/didactics/"],"se":["https://w3id.org/reliedu/didactics/"],"bels":["https://w3id.org/reliedu/didactics/"],"bel":["https://w3id.org/reliedu/didactics/"],"be":["https://w3id.org/reliedu/didactics/"],"b":["https://w3id.org/reliedu/didactics/"],"els":["https://w3id.org/reliedu/didactics/"],"ls":["https://w3id.org/reliedu/didactics/"],"entify":["https://w3id.org/reliedu/didactics/"],"entif":["https://w3id.org/reliedu/didactics/"],"enti":["https://w3id.org/reliedu/didactics/"],"ent":["https://w3id.org/reliedu/didactics/"],"en":["https://w3id.org/reliedu/didactics/"],"ntify":["https://w3id.org/reliedu/didactics/"],"ntif":["https://w3id.org/reliedu/didactics/"],"nti":["https://w3id.org/reliedu/didactics/"],"nt":["https://w3id.org/reliedu/didactics/"],"tify":["https://w3id.org/reliedu/didactics/"],"tif":["https://w3id.org/reliedu/didactics/"],"ify":["https://w3id.org/reliedu/didactics/"],"orientation":["https://w3id.org/reliedu/didactics/"],"orientatio":["https://w3id.org/reliedu/didactics/"],"orientati":["https://w3id.org/reliedu/didactics/"],"orientat":["https://w3id.org/reliedu/didactics/"],"orienta":["https://w3id.org/reliedu/didactics/"],"orient":["https://w3id.org/reliedu/didactics/"],"orien":["https://w3id.org/reliedu/didactics/"],"orie":["https://w3id.org/reliedu/didactics/"],"ori":["https://w3id.org/reliedu/didactics/"],"or":["https://w3id.org/reliedu/didactics/"],"rientation":["https://w3id.org/reliedu/didactics/"],"rientatio":["https://w3id.org/reliedu/didactics/"],"rientati":["https://w3id.org/reliedu/didactics/"],"rientat":["https://w3id.org/reliedu/didactics/"],"rienta":["https://w3id.org/reliedu/didactics/"],"rient":["https://w3id.org/reliedu/didactics/"],"rien":["https://w3id.org/reliedu/didactics/"],"rie":["https://w3id.org/reliedu/didactics/"],"ientation":["https://w3id.org/reliedu/didactics/"],"ientatio":["https://w3id.org/reliedu/didactics/"],"ientati":["https://w3id.org/reliedu/didactics/"],"ientat":["https://w3id.org/reliedu/didactics/"],"ienta":["https://w3id.org/reliedu/didactics/"],"ient":["https://w3id.org/reliedu/didactics/"],"ien":["https://w3id.org/reliedu/didactics/"],"ie":["https://w3id.org/reliedu/didactics/"],"entation":["https://w3id.org/reliedu/didactics/"],"entatio":["https://w3id.org/reliedu/didactics/"],"entati":["https://w3id.org/reliedu/didactics/"],"entat":["https://w3id.org/reliedu/didactics/"],"enta":["https://w3id.org/reliedu/didactics/"],"ntation":["https://w3id.org/reliedu/didactics/"],"ntatio":["https://w3id.org/reliedu/didactics/"],"ntati":["https://w3id.org/reliedu/didactics/"],"ntat":["https://w3id.org/reliedu/didactics/"],"nta":["https://w3id.org/reliedu/didactics/"],"pedagogical":["https://w3id.org/reliedu/didactics/"],"pedagogica":["https://w3id.org/reliedu/didactics/"],"pedagogic":["https://w3id.org/reliedu/didactics/"],"pedagogi":["https://w3id.org/reliedu/didactics/"],"pedagog":["https://w3id.org/reliedu/didactics/"],"pedago":["https://w3id.org/reliedu/didactics/"],"pedag":["https://w3id.org/reliedu/didactics/"],"peda":["https://w3id.org/reliedu/didactics/"],"ped":["https://w3id.org/reliedu/didactics/"],"edagogical":["https://w3id.org/reliedu/didactics/"],"edagogica":["https://w3id.org/reliedu/didactics/"],"edagogic":["https://w3id.org/reliedu/didactics/"],"edagogi":["https://w3id.org/reliedu/didactics/"],"edagog":["https://w3id.org/reliedu/didactics/"],"edago":["https://w3id.org/reliedu/didactics/"],"edag":["https://w3id.org/reliedu/didactics/"],"eda":["https://w3id.org/reliedu/didactics/"],"educational":["https://w3id.org/reliedu/didactics/"],"educationa":["https://w3id.org/reliedu/didactics/"]},{"fy":["https://w3id.org/reliedu/didactics/"],"y":["https://w3id.org/reliedu/didactics/"],"tation":["https://w3id.org/reliedu/didactics/"],"tatio":["https://w3id.org/reliedu/didactics/"],"tati":["https://w3id.org/reliedu/didactics/"],"tat":["https://w3id.org/reliedu/didactics/"],"ta":["https://w3id.org/reliedu/didactics/"],"dagogical":["https://w3id.org/reliedu/didactics/"],"dagogica":["https://w3id.org/reliedu/didactics/"],"dagogic":["https://w3id.org/reliedu/didactics/"],"dagogi":["https://w3id.org/reliedu/didactics/"],"dagog":["https://w3id.org/reliedu/didactics/"],"dago":["https://w3id.org/reliedu/didactics/"],"dag":["https://w3id.org/reliedu/didactics/"],"agogical":["https://w3id.org/reliedu/didactics/"],"agogica":["https://w3id.org/reliedu/didactics/"],"agogic":["https://w3id.org/reliedu/didactics/"],"agogi":["https://w3id.org/reliedu/didactics/"],"agog":["https://w3id.org/reliedu/didactics/"],"ago":["https://w3id.org/reliedu/didactics/"],"ag":["https://w3id.org/reliedu/didactics/"],"gogical":["https://w3id.org/reliedu/didactics/"],"gogica":["https://w3id.org/reliedu/didactics/"],"gogic":["https://w3id.org/reliedu/didactics/"],"gogi":["https://w3id.org/reliedu/didactics/"],"gog":["https://w3id.org/reliedu/didactics/"],"go":["https://w3id.org/reliedu/didactics/"],"ogical":["https://w3id.org/reliedu/didactics/"],"ogica":["https://w3id.org/reliedu/didactics/"],"ogic":["https://w3id.org/reliedu/didactics/"],"ogi":["https://w3id.org/reliedu/didactics/"],"og":["https://w3id.org/reliedu/didactics/"],"ducational":["https://w3id.org/reliedu/didactics/"],"ducationa":["https://w3id.org/reliedu/didactics/"],"ucational":["https://w3id.org/reliedu/didactics/"],"ucationa":["https://w3id.org/reliedu/didactics/"],"cational":["https://w3id.org/reliedu/didactics/"],"cationa":["https://w3id.org/reliedu/didactics/"],"ational":["https://w3id.org/reliedu/didactics/"],"ationa":["https://w3id.org/reliedu/didactics/"],"resources":["https://w3id.org/reliedu/didactics/"],"resource":["https://w3id.org/reliedu/didactics/"],"resourc":["https://w3id.org/reliedu/didactics/"],"resour":["https://w3id.org/reliedu/didactics/"],"resou":["https://w3id.org/reliedu/didactics/"],"reso":["https://w3id.org/reliedu/didactics/"],"res":["https://w3id.org/reliedu/didactics/"],"esources":["https://w3id.org/reliedu/didactics/"],"esource":["https://w3id.org/reliedu/didactics/"],"esourc":["https://w3id.org/reliedu/didactics/"],"esour":["https://w3id.org/reliedu/didactics/"],"esou":["https://w3id.org/reliedu/didactics/"],"eso":["https://w3id.org/reliedu/didactics/"],"sources":["https://w3id.org/reliedu/didactics/"],"source":["https://w3id.org/reliedu/didactics/"],"sourc":["https://w3id.org/reliedu/didactics/"],"sour":["https://w3id.org/reliedu/didactics/"],"sou":["https://w3id.org/reliedu/didactics/"],"so":["https://w3id.org/reliedu/didactics/"]},{"of":["https://w3id.org/reliedu/didactics/"],"gical":["https://w3id.org/reliedu/didactics/"],"gica":["https://w3id.org/reliedu/didactics/"],"gic":["https://w3id.org/reliedu/didactics/"],"ical":["https://w3id.org/reliedu/didactics/"],"ica":["https://w3id.org/reliedu/didactics/"],"cal":["https://w3id.org/reliedu/didactics/"],"tional":["https://w3id.org/reliedu/didactics/"],"tiona":["https://w3id.org/reliedu/didactics/"],"ional":["https://w3id.org/reliedu/didactics/"],"iona":["https://w3id.org/reliedu/didactics/"],"onal":["https://w3id.org/reliedu/didactics/"],"ona":["https://w3id.org/reliedu/didactics/"],"nal":["https://w3id.org/reliedu/didactics/"],"na":["https://w3id.org/reliedu/didactics/"],"ources":["https://w3id.org/reliedu/didactics/"],"ource":["https://w3id.org/reliedu/didactics/"],"ourc":["https://w3id.org/reliedu/didactics/"],"our":["https://w3id.org/reliedu/didactics/"],"urces":["https://w3id.org/reliedu/didactics/"],"urce":["https://w3id.org/reliedu/didactics/"],"urc":["https://w3id.org/reliedu/didactics/"],"ur":["https://w3id.org/reliedu/didactics/"],"rces":["https://w3id.org/reliedu/didactics/"],"rce":["https://w3id.org/reliedu/didactics/"],"rc":["https://w3id.org/reliedu/didactics/"],"ces":["https://w3id.org/reliedu/didactics/"],"ce":["https://w3id.org/reliedu/didactics/"]},{}]